huihe/__init__.py
huihe/device/HuiHeClimate.py
huihe/device/HuiHeIR.py
huihe/device/HuiHeMediaPlayer.py
huihe/device/__init__.py
huihe/device/base.py
huihe/device/climateConst.py
huihe/device/const.py
huihe/device/constant.py
huihe/device/get_huihe_device.py
huihe/device/huiHeLight.py
huihe/device/huiHeSwitch.py
huihe/device/iFutureHomeapi.py
huihe/device/log.py
huihe/device/mediaPlayerConst.py
huihe-0.0.4.dist-info/METADATA
huihe-0.0.4.dist-info/WHEEL
huihe-0.0.4.dist-info/top_level.txt
huihe-0.0.4.dist-info/RECORD
