Metadata-Version: 2.1
Name: huihe
Version: 0.0.4
Summary: ifuturehome
Home-page: https://github.com/
Author: xlh
Author-email: lihong.xie@huihetech.cn
License: UNKNOWN
Platform: UNKNOWN
Classifier: Programming Language :: Python :: 3
Classifier: License :: OSI Approved :: MIT License
Classifier: Operating System :: OS Independent
